CONTRIBUTING.md
aws_advanced_python_wrapper/__init__.py
aws_advanced_python_wrapper/allowed_and_blocked_hosts.py
aws_advanced_python_wrapper/aurora_connection_tracker_plugin.py
aws_advanced_python_wrapper/aurora_initial_connection_strategy_plugin.py
aws_advanced_python_wrapper/aws_secrets_manager_plugin.py
aws_advanced_python_wrapper/blue_green_plugin.py
aws_advanced_python_wrapper/connect_time_plugin.py
aws_advanced_python_wrapper/connection_provider.py
aws_advanced_python_wrapper/credentials_provider_factory.py
aws_advanced_python_wrapper/custom_endpoint_plugin.py
aws_advanced_python_wrapper/database_dialect.py
aws_advanced_python_wrapper/default_plugin.py
aws_advanced_python_wrapper/developer_plugin.py
aws_advanced_python_wrapper/driver_configuration_profiles.py
aws_advanced_python_wrapper/driver_dialect.py
aws_advanced_python_wrapper/driver_dialect_codes.py
aws_advanced_python_wrapper/driver_dialect_manager.py
aws_advanced_python_wrapper/driver_info.py
aws_advanced_python_wrapper/errors.py
aws_advanced_python_wrapper/exception_handling.py
aws_advanced_python_wrapper/execute_time_plugin.py
aws_advanced_python_wrapper/failover_plugin.py
aws_advanced_python_wrapper/failover_result.py
aws_advanced_python_wrapper/fastest_response_strategy_plugin.py
aws_advanced_python_wrapper/federated_plugin.py
aws_advanced_python_wrapper/host_availability.py
aws_advanced_python_wrapper/host_list_provider.py
aws_advanced_python_wrapper/host_monitoring_plugin.py
aws_advanced_python_wrapper/host_monitoring_v2_plugin.py
aws_advanced_python_wrapper/host_selector.py
aws_advanced_python_wrapper/hostinfo.py
aws_advanced_python_wrapper/iam_plugin.py
aws_advanced_python_wrapper/limitless_plugin.py
aws_advanced_python_wrapper/mysql_driver_dialect.py
aws_advanced_python_wrapper/okta_plugin.py
aws_advanced_python_wrapper/pep249.py
aws_advanced_python_wrapper/pg_driver_dialect.py
aws_advanced_python_wrapper/plugin.py
aws_advanced_python_wrapper/plugin_service.py
aws_advanced_python_wrapper-1.4.0.dist-info/LICENSE
aws_advanced_python_wrapper-1.4.0.dist-info/METADATA
aws_advanced_python_wrapper-1.4.0.dist-info/NOTICE
aws_advanced_python_wrapper-1.4.0.dist-info/WHEEL
aws_advanced_python_wrapper-1.4.0.dist-info/RECORD
