Metadata-Version: 2.1
Name: aws_advanced_python_wrapper
Version: 1.4.0
Summary: Amazon Web Services (AWS) Advanced Python Wrapper
Home-page: https://github.com/awslabs/aws-advanced-python-wrapper
License: Apache-2.0
Author: Amazon Web Services
Requires-Python: >=3.8.1,<4.0.0
Classifier: Development Status :: 5 - Production/Stable
Classifier: Intended Audience :: Developers
Classifier: License :: OSI Approved :: Apache Software License
Classifier: Natural Language :: English
Classifier: Programming Language :: Python
Classifier: Programming Language :: Python :: 3
Classifier: Programming Language :: Python :: 3.9
Classifier: Programming Language :: Python :: 3.10
Classifier: Programming Language :: Python :: 3.11
Classifier: Programming Language :: Python :: 3.12
Classifier: Programming Language :: Python :: 3 :: Only
Classifier: Programming Language :: Python :: 3.8
Requires-Dist: aws-xray-sdk (>=2.13.1,<3.0.0)
Requires-Dist: boto3 (>=1.34.111,<2.0.0)
Requires-Dist: opentelemetry-api (>=1.22.0,<2.0.0)
Requires-Dist: opentelemetry-sdk (>=1.22.0,<2.0.0)
Requires-Dist: requests (>=2.32.2,<3.0.0)
Requires-Dist: resourcebundle (==2.1.0)
Requires-Dist: toml (>=0.10.2,<0.11.0)
Requires-Dist: types_aws_xray_sdk (>=2.13.0,<3.0.0)
Project-URL: Documentation, https://github.com/awslabs/aws-advanced-python-wrapper/docs/
Project-URL: Repository, https://github.com/awslabs/aws-advanced-python-wrapper
